bleu/__init__.py
bleu/bleu.py
bleu/download.py
bleu-0.2.dist-info/LICENSE
bleu-0.2.dist-info/METADATA
bleu-0.2.dist-info/WHEEL
bleu-0.2.dist-info/top_level.txt
bleu-0.2.dist-info/RECORD
