Metadata-Version: 2.1
Name: bleu
Version: 0.2
Summary: A Python Wrapper to calculate standard BLEU scores for NLP
Home-page: https://github.com/zhijing-jin/bleu
Author: Zhijing Jin
Author-email: zhijing.jin@connect.hku.hk
License: BSD 3-Clause
Platform: UNKNOWN
Requires-Dist: efficiency
